pyyawt/__config__.py
pyyawt/__init__.py
pyyawt/_pyyawt.pyd
pyyawt/cowt.py
pyyawt/cwt.py
pyyawt/denoising.py
pyyawt/dwt.py
pyyawt/dwt1d.py
pyyawt/dwt2d.py
pyyawt/dwt3d.py
pyyawt/setup.py
pyyawt/swt.py
pyyawt/utility.py
pyyawt/version.py
pyyawt/tests/test_biorwavf.py
pyyawt/tests/test_coifwavf.py
pyyawt/tests/test_conv.py
pyyawt/tests/test_dbwavf.py
pyyawt/tests/test_detcoef.py
pyyawt/tests/test_dwt.py
pyyawt/tests/test_dwtfilt.py
pyyawt/tests/test_dwtmode.py
pyyawt/tests/test_dyaddown.py
pyyawt/tests/test_dyadup.py
pyyawt/tests/test_idwt.py
pyyawt/tests/test_legdwavf.py
pyyawt/tests/test_qmf.py
pyyawt/tests/test_rbiorwavf.py
pyyawt/tests/test_symwavf.py
pyyawt/tests/test_wavedec.py
pyyawt/tests/test_waverec.py
pyyawt/tests/test_wextend.py
pyyawt/tests/test_wfilters.py
pyyawt/tests/test_wkeep.py
pyyawt/tests/test_wmaxlev.py
pyyawt/tests/data/Data.npz
pyyawt-0.1.1.dist-info/DESCRIPTION.rst
pyyawt-0.1.1.dist-info/METADATA
pyyawt-0.1.1.dist-info/RECORD
pyyawt-0.1.1.dist-info/WHEEL
pyyawt-0.1.1.dist-info/metadata.json
pyyawt-0.1.1.dist-info/top_level.txt
